Desafio_projeto_banco/Desafio_projeto_banco.py
Desafio_projeto_banco/__init__.py
desafio_projeto_banco-1.4.25.2.dist-info/licenses/LICENSE
desafio_projeto_banco-1.4.25.2.dist-info/METADATA
desafio_projeto_banco-1.4.25.2.dist-info/WHEEL
desafio_projeto_banco-1.4.25.2.dist-info/top_level.txt
desafio_projeto_banco-1.4.25.2.dist-info/RECORD
