Metadata-Version: 2.4
Name: Desafio_projeto_banco
Version: 1.4.25.2
Summary: É um projeto de banco, um desafio proposto pela DIO.
Home-page: https://github.com/mekaroi/Desafio_projeto_banco
Author: Igor Mekaro
Author-email: iguinhoo.msn@hotmail.com
License: MIT,
Requires-Python: >=3.6
License-File: LICENSE
Dynamic: author
Dynamic: author-email
Dynamic: description
Dynamic: description-content-type
Dynamic: home-page
Dynamic: license
Dynamic: license-file
Dynamic: requires-python
Dynamic: summary
